AUTHORS.rst
HISTORY.rst
LICENSE.rst
MANIFEST.in
README.rst
setup.py
RandomThings.egg-info/PKG-INFO
RandomThings.egg-info/SOURCES.txt
RandomThings.egg-info/dependency_links.txt
RandomThings.egg-info/top_level.txt
random_things/__init__.py
random_things/randomer.py
random_things/names_csv/__init__.py
random_things/names_csv/all_names.csv
random_things/names_csv/census-derived-all-first.csv
random_things/names_csv/census-dist-female-first.csv
random_things/names_csv/census-dist-male-first.csv
random_things/names_csv/nicknames.csv
random_things/random_sources/__init__.py
random_things/random_sources/democoursedata.py
random_things/random_sources/flowers.csv
random_things/random_sources/flowers.py
random_things/random_sources/high_school_musicals.py
random_things/random_sources/job_titles.py
random_things/random_sources/onomatopoeia.py
random_things/random_sources/presidents.csv
random_things/random_sources/presidents.py
random_things/random_sources/state_capitals.py
randomthings.egg-info/PKG-INFO
randomthings.egg-info/SOURCES.txt
randomthings.egg-info/dependency_links.txt
randomthings.egg-info/top_level.txt
tests/random_things_test.py